{"count":3306,"page":1,"first":1,"last":30,"hits":30,"carrier":0,"pageCount":100,"Items":[{"Item":{"title":"湖西線12×4の謎","titleKana":"コセイセン ジュウニ カケル シ ノ ナゾ","subTitle":"","subTitleKana":"","seriesName":"Ｔｏｋｕｍａ　ｎｏｖｅｌｓ","seriesNameKana":"トクマ ノベルズ","contents":"","author":"西村京太郎","authorKana":"ニシムラ,キョウタロウ","publisherName":"徳間書店","size":"新書","isbn":"9784198509347","itemCaption":"","salesDate":"2013年08月09日","itemPrice":900,"listPrice":900,"discountRate":0,"discountPrice":0,"itemUrl":"http://books.rakuten.co.jp/rb/12384596/","affiliateUrl":"","smallImageUrl":"http://thumbnail.image.rakuten.co.jp/@0_mall/book/cabinet/9347/9784198509347.jpg?_ex=64x64","mediumImageUrl":"http://thumbnail.image.rakuten.co.jp/@0_mall/book/cabinet/9347/9784198509347.jpg?_ex=120x120","largeImageUrl":"http://thumbnail.image.rakuten.co.jp/@0_mall/book/cabinet/9347/9784198509347.jpg?_ex=200x200","chirayomiUrl":"","availability":"1","postageFlag":0,"limitedFlag":0,"reviewCount":1,"reviewAverage":"5.0","booksGenreId":"001004008005"}},{"Item":{"title":"双孔堂の殺人","titleKana":"ソウコウドウ ノ サツジン","subTitle":"Ｄｏｕｂｌｅ　Ｔｏｒｕｓ","subTitleKana":"ダブル トーラス","seriesName":"講談社ノベルス","seriesNameKana":"コウダンシャ ノベルス","contents":"","author":"周木律","authorKana":"シュウキ,リツ","publisherName":"講談社","size":"新書","isbn":"9784061828834","itemCaption":"","salesDate":"2013年08月07日","itemPrice":924,"listPrice":924,"discountRate":0,"discountPrice":0,"itemUrl":"http://books.rakuten.co.jp/rb/12375686/","affiliateUrl":"","smallImageUrl":"http://thumbnail.image.rakuten.co.jp/@0_mall/book/cabinet/8834/9784061828834.jpg?_ex=64x64","mediumImageUrl":"http://thumbnail.image.rakuten.co.jp/@0_mall/book/cabinet/8834/9784061828834.jpg?_ex=120x120","largeImageUrl":"http://thumbnail.image.rakuten.co.jp/@0_mall/book/cabinet/8834/9784061828834.jpg?_ex=200x200","chirayomiUrl":"","availability":"1","postageFlag":0,"limitedFlag":0,"reviewCount":0,"reviewAverage":"0.0","booksGenreId":"001004008003"}},{"Item":{"title":"タイタニア（1〈疾風篇〉2〈暴風篇〉3〈旋）","titleKana":"タイタニア","subTitle":"","subTitleKana":"","seriesName":"講談社ノベルス","seriesNameKana":"コウダンシャ ノベルス","contents":"","author":"田中芳樹","authorKana":"タナカ,ヨシキ","publisherName":"講談社","size":"新書","isbn":"9784061828865","itemCaption":"","salesDate":"2013年08月07日","itemPrice":1575,"listPrice":1575,"discountRate":0,"discountPrice":0,"itemUrl":"http://books.rakuten.co.jp/rb/12386926/","affiliateUrl":"","smallImageUrl":"http://thumbnail.image.rakuten.co.jp/@0_mall/book/cabinet/8865/9784061828865.jpg?_ex=64x64","mediumImageUrl":"http://thumbnail.image.rakuten.co.jp/@0_mall/book/cabinet/8865/9784061828865.jpg?_ex=120x120","largeImageUrl":"http://thumbnail.image.rakuten.co.jp/@0_mall/book/cabinet/8865/9784061828865.jpg?_ex=200x200","chirayomiUrl":"","availability":"1","postageFlag":1,"limitedFlag":0,"reviewCount":0,"reviewAverage":"0.0","booksGenreId":"001004008004"}},{"Item":{"title":"愛の徴","titleKana":"アイ ノ シルシ","subTitle":"天国の方角","subTitleKana":"テンゴク ノ ホウガク","seriesName":"講談社ノベルス","seriesNameKana":"コウダンシャ ノベルス","contents":"","author":"近本洋一","authorKana":"チカモト,ヨウイチ","publisherName":"講談社","size":"新書","isbn":"9784061828803","itemCaption":"","salesDate":"2013年08月07日","itemPrice":1617,"listPrice":1617,"discountRate":0,"discountPrice":0,"itemUrl":"http://books.rakuten.co.jp/rb/12419906/","affiliateUrl":"","smallImageUrl":"http://thumbnail.image.rakuten.co.jp/@0_mall/book/cabinet/8803/9784061828803.jpg?_ex=64x64","mediumImageUrl":"http://thumbnail.image.rakuten.co.jp/@0_mall/book/cabinet/8803/9784061828803.jpg?_ex=120x120","largeImageUrl":"http://thumbnail.image.rakuten.co.jp/@0_mall/book/cabinet/8803/9784061828803.jpg?_ex=200x200","chirayomiUrl":"","availability":"1","postageFlag":1,"limitedFlag":0,"reviewCount":0,"reviewAverage":"0.0","booksGenreId":"001004008004"}},{"Item":{"title":"さくらゆき","titleKana":"サクラ ユキ","subTitle":"桜井京介ｒｅｔｕｒｎｓ","subTitleKana":"サクライ キョウスケ リターンズ","seriesName":"講談社ノベルス","seriesNameKana":"コウダンシャ ノベルス","contents":"","author":"篠田真由美","authorKana":"シノダ,マユミ","publisherName":"講談社","size":"新書","isbn":"9784061828841","itemCaption":"","salesDate":"2013年08月07日","itemPrice":945,"listPrice":945,"discountRate":0,"discountPrice":0,"itemUrl":"http://books.rakuten.co.jp/rb/12375687/","affiliateUrl":"","smallImageUrl":"http://thumbnail.image.rakuten.co.jp/@0_mall/book/cabinet/8841/9784061828841.jpg?_ex=64x64","mediumImageUrl":"http://thumbnail.image.rakuten.co.jp/@0_mall/book/cabinet/8841/9784061828841.jpg?_ex=120x120","largeImageUrl":"http://thumbnail.image.rakuten.co.jp/@0_mall/book/cabinet/8841/9784061828841.jpg?_ex=200x200","chirayomiUrl":"","availability":"1","postageFlag":0,"limitedFlag":0,"reviewCount":1,"reviewAverage":"3.0","booksGenreId":"001004008003"}},{"Item":{"title":"セカンドタウン","titleKana":"セカンド タウン","subTitle":"","subTitleKana":"","seriesName":"講談社ノベルス","seriesNameKana":"コウダンシャ ノベルス","contents":"","author":"嶋戸悠祐","authorKana":"シマト,ユウスケ","publisherName":"講談社","size":"新書","isbn":"9784061828858","itemCaption":"","salesDate":"2013年08月07日","itemPrice":945,"listPrice":945,"discountRate":0,"discountPrice":0,"itemUrl":"http://books.rakuten.co.jp/rb/12386925/","affiliateUrl":"","smallImageUrl":"http://thumbnail.image.rakuten.co.jp/@0_mall/book/cabinet/8858/9784061828858.jpg?_ex=64x64","mediumImageUrl":"http://thumbnail.image.rakuten.co.jp/@0_mall/book/cabinet/8858/9784061828858.jpg?_ex=120x120","largeImageUrl":"http://thumbnail.image.rakuten.co.jp/@0_mall/book/cabinet/8858/9784061828858.jpg?_ex=200x200","chirayomiUrl":"","availability":"1","postageFlag":0,"limitedFlag":0,"reviewCount":0,"reviewAverage":"0.0","booksGenreId":"001004008003"}},{"Item":{"title":"つむじ風食堂と僕","titleKana":"ツムジカゼ ショクドウ ト ボク","subTitle":"","subTitleKana":"","seriesName":"ちくまプリマー新書","seriesNameKana":"チクマ プリマー シンショ","contents":"","author":"吉田篤弘","authorKana":"ヨシダ,アツヒロ","publisherName":"筑摩書房","size":"新書","isbn":"9784480689023","itemCaption":"少し大人びた少年リツ君１２歳。つむじ風食堂のテーブルで、町の大人たちがリツ君に「仕事」の話をする。リツ君は何を思い、何を考えるか…。人気シリーズ「月舟町三部作」番外篇。","salesDate":"2013年08月05日","itemPrice":714,"listPrice":714,"discountRate":0,"discountPrice":0,"itemUrl":"http://books.rakuten.co.jp/rb/12410427/","affiliateUrl":"","smallImageUrl":"http://thumbnail.image.rakuten.co.jp/@0_mall/book/cabinet/9023/9784480689023.jpg?_ex=64x64","mediumImageUrl":"http://thumbnail.image.rakuten.co.jp/@0_mall/book/cabinet/9023/9784480689023.jpg?_ex=120x120","largeImageUrl":"http://thumbnail.image.rakuten.co.jp/@0_mall/book/cabinet/9023/9784480689023.jpg?_ex=200x200","chirayomiUrl":"","availability":"1","postageFlag":0,"limitedFlag":0,"reviewCount":0,"reviewAverage":"0.0","booksGenreId":"001004008008"}},{"Item":{"title":"はつゆきさくら(仮)","titleKana":"ハツユキサクラカリ","subTitle":"","subTitleKana":"","seriesName":"ＳＥＬＥＮ　ＮＯＶＥＬＳ","seriesNameKana":"セレン ノベルス","contents":"","author":"水無瀬さんご/SAGAPLANETS","authorKana":"ミナセサンゴ/サガプラネッツ","publisherName":"一迅社","size":"新書","isbn":"9784758044714","itemCaption":"今年最初の雪が降った１２月。初雪は旧市街の一画で、真っ白なドレスを着た美しい少女に出会う。雪に降られながら、少女は一匹のウサギを探して街をさまよっていた。一夜の不思議な出会い。そして数日後。学園にドレスの少女、「桜」が転校してくる。最後の冬へ、初雪を連れて行くために。めぐる春夏秋冬。終わる１０９５日。やがて冬を越えて、春が訪れる頃。ついに積もることのなかった雪の思い出を抱いて、少年は立ち尽くす。ＳＡＧＡ　ＰＬＡＮＥＴＳの贈る大ヒットアドベンチャーＰＣゲーム『はつゆきさくら』のノベライズ。","salesDate":"2013年08月02日","itemPrice":890,"listPrice":890,"discountRate":0,"discountPrice":0,"itemUrl":"http://books.rakuten.co.jp/rb/12343136/","affiliateUrl":"","smallImageUrl":"http://thumbnail.image.rakuten.co.jp/@0_mall/book/cabinet/4714/9784758044714.jpg?_ex=64x64","mediumImageUrl":"http://thumbnail.image.rakuten.co.jp/@0_mall/book/cabinet/4714/9784758044714.jpg?_ex=120x120","largeImageUrl":"http://thumbnail.image.rakuten.co.jp/@0_mall/book/cabinet/4714/9784758044714.jpg?_ex=200x200","chirayomiUrl":"","availability":"1","postageFlag":0,"limitedFlag":0,"reviewCount":0,"reviewAverage":"0.0","booksGenreId":"001004008009/001008022008"}},{"Item":{"title":"Eden","titleKana":"エデン","subTitle":"白衣の原罪","subTitleKana":"ハクイ ノ ゲンザイ","seriesName":"Ｃｒｏｓｓ　ｎｏｖｅｌｓ","seriesNameKana":"クロス ノベルス","contents":"","author":"日向唯稀","authorKana":"ヒュウガ,ユキ","publisherName":"笠倉出版社","size":"新書","isbn":"9784773086706","itemCaption":"","salesDate":"2013年08月","itemPrice":935,"listPrice":935,"discountRate":0,"discountPrice":0,"itemUrl":"http://books.rakuten.co.jp/rb/12428838/","affiliateUrl":"","smallImageUrl":"http://thumbnail.image.rakuten.co.jp/@0_mall/book/cabinet/6706/9784773086706.jpg?_ex=64x64","mediumImageUrl":"http://thumbnail.image.rakuten.co.jp/@0_mall/book/cabinet/6706/9784773086706.jpg?_ex=120x120","largeImageUrl":"http://thumbnail.image.rakuten.co.jp/@0_mall/book/cabinet/6706/9784773086706.jpg?_ex=200x200","chirayomiUrl":"","availability":"1","postageFlag":0,"limitedFlag":0,"reviewCount":0,"reviewAverage":"0.0","booksGenreId":"001004008006"}},{"Item":{"title":"愛ゆえに、でございます","titleKana":"アイ ユエニ デ ゴザイマス","subTitle":"","subTitleKana":"","seriesName":"Ｃｒｏｓｓ　ｎｏｖｅｌｓ","seriesNameKana":"クロス ノベルス","contents":"","author":"ｃｈｉ-ｃｏ","authorKana":"チーコ","publisherName":"笠倉出版社","size":"新書","isbn":"9784773086720","itemCaption":"","salesDate":"2013年08月","itemPrice":935,"listPrice":935,"discountRate":0,"discountPrice":0,"itemUrl":"http://books.rakuten.co.jp/rb/12428837/","affiliateUrl":"","smallImageUrl":"http://thumbnail.image.rakuten.co.jp/@0_mall/book/cabinet/6720/9784773086720.jpg?_ex=64x64","mediumImageUrl":"http://thumbnail.image.rakuten.co.jp/@0_mall/book/cabinet/6720/9784773086720.jpg?_ex=120x120","largeImageUrl":"http://thumbnail.image.rakuten.co.jp/@0_mall/book/cabinet/6720/9784773086720.jpg?_ex=200x200","chirayomiUrl":"","availability":"1","postageFlag":0,"limitedFlag":0,"reviewCount":0,"reviewAverage":"0.0","booksGenreId":"001004008004"}},{"Item":{"title":"俺のボカロが妹になりたそうにこちらを見ている","titleKana":"オレノボカロガイモウトニナリタソウニコチラヲミテイル","subTitle":"","subTitleKana":"","seriesName":"","seriesNameKana":"","contents":"","author":"デッドボールＰ/Nidy-2D-、かる、さくらねこ、なぎみそ、yuna","authorKana":"デッドボールピー/ニディカルサクラネコナギミソユナ","publisherName":"一迅社","size":"新書","isbn":"9784758044707","itemCaption":"","salesDate":"2013年08月01日","itemPrice":1260,"listPrice":1260,"discountRate":0,"discountPrice":0,"itemUrl":"http://books.rakuten.co.jp/rb/12351475/","affiliateUrl":"","smallImageUrl":"http://thumbnail.image.rakuten.co.jp/@0_mall/book/cabinet/4707/9784758044707.jpg?_ex=64x64","mediumImageUrl":"http://thumbnail.image.rakuten.co.jp/@0_mall/book/cabinet/4707/9784758044707.jpg?_ex=120x120","largeImageUrl":"http://thumbnail.image.rakuten.co.jp/@0_mall/book/cabinet/4707/9784758044707.jpg?_ex=200x200","chirayomiUrl":"","availability":"1","postageFlag":0,"limitedFlag":0,"reviewCount":0,"reviewAverage":"0.0","booksGenreId":"001004008004/001004008005"}},{"Item":{"title":"平安異聞君ありてこそ","titleKana":"ヘイアン イブン キミ アリテ コソ","subTitle":"","subTitleKana":"","seriesName":"ＡＺ　ｎｏｖｅｌｓ","seriesNameKana":"アズ ノベルズ","contents":"","author":"牧山とも","authorKana":"マキヤマ,トモ","publisherName":"イースト・プレス","size":"新書","isbn":"9784781610320","itemCaption":"斎王自害の謎、それに関わる何者かの企みを探るよう今上帝から命じられた図書頭・匡深。希代の秀才でやや厭世的なところのある匡深は、実は時空の狭間を往来し、平素は見えぬ右目で過去と未来を視ることができる『時渡り』の異能者だった。思いがけず帝の実弟・陽仁と共に隠密任務につくことになった匡深だが、自由闊達な陽仁から予期せぬ接近を図られ困惑するはめに。しっとり艶雅な平安幻想異聞の結末は…。","salesDate":"2013年08月","itemPrice":893,"listPrice":893,"discountRate":0,"discountPrice":0,"itemUrl":"http://books.rakuten.co.jp/rb/12411531/","affiliateUrl":"","smallImageUrl":"http://thumbnail.image.rakuten.co.jp/@0_mall/book/cabinet/0320/9784781610320.jpg?_ex=64x64","mediumImageUrl":"http://thumbnail.image.rakuten.co.jp/@0_mall/book/cabinet/0320/9784781610320.jpg?_ex=120x120","largeImageUrl":"http://thumbnail.image.rakuten.co.jp/@0_mall/book/cabinet/0320/9784781610320.jpg?_ex=200x200","chirayomiUrl":"","availability":"1","postageFlag":0,"limitedFlag":0,"reviewCount":0,"reviewAverage":"0.0","booksGenreId":"001004008007/001021001013"}},{"Item":{"title":"邪神たちの2・26〔新装版〕","titleKana":"ジャシンタチ ノ ニニロク","subTitle":"","subTitleKana":"","seriesName":"クトゥルー・ミュトス・ファイルズ","seriesNameKana":"クトゥルー ミュトス ファイルズ","contents":"","author":"田中文雄","authorKana":"タナカ,フミオ","publisherName":"創土社","size":"新書","isbn":"9784798830070","itemCaption":"大日本帝国陸軍将校、海江田清一は、九頭竜川上流の故郷で父の遺品を発見する。そこには船乗りだった父の、インスマスの町で体験した怪異が綴られた遺書と、ハワードという友人からの手紙が隠されていた。そして、１９３６年２月２６日、陸軍の青年将校らは１４８３名の兵を率い、「昭和維新断行・尊皇討奸」を掲げて決起する。しかしその真の目的は、邪神の魔の手から日本を救うことであった。","salesDate":"2013年08月","itemPrice":1050,"listPrice":1050,"discountRate":0,"discountPrice":0,"itemUrl":"http://books.rakuten.co.jp/rb/12409917/","affiliateUrl":"","smallImageUrl":"http://thumbnail.image.rakuten.co.jp/@0_mall/book/cabinet/0070/9784798830070.jpg?_ex=64x64","mediumImageUrl":"http://thumbnail.image.rakuten.co.jp/@0_mall/book/cabinet/0070/9784798830070.jpg?_ex=120x120","largeImageUrl":"http://thumbnail.image.rakuten.co.jp/@0_mall/book/cabinet/0070/9784798830070.jpg?_ex=200x200","chirayomiUrl":"","availability":"1","postageFlag":0,"limitedFlag":0,"reviewCount":0,"reviewAverage":"0.0","booksGenreId":"001004008004"}},{"Item":{"title":"碧のかたみ","titleKana":"アオ ノ カタミ","subTitle":"","subTitleKana":"","seriesName":"Ｈｏｌｌｙ　ｎｏｖｅｌｓ","seriesNameKana":"ホーリー ノベルス","contents":"","author":"尾上与一","authorKana":"オガミ,ヨイチ","publisherName":"蒼竜社","size":"新書","isbn":"9784883864201","itemCaption":"昭和十八年。全盛を誇る南の要塞・ラバウル航空隊に着任した六郎は、喧嘩に明け暮れている戦闘機乗り・琴平恒に出会う。問題児だが操縦士として優秀な恒と「夜間戦闘機・月光」でペアを組むことになった六郎は、行動を共にするうちに、故郷の家族を守りたいという彼の深い思いと純粋さに触れ恒に強く惹かれていく。命の危険と隣り合わせの日々が続く中、二人は互いを大切なペアとしていとしく思うように。しかし、ラバウルにも敗戦の足音は確実に近づいていた…。「天球儀の海」希の兄・恒と六郎の命を懸けた青春の日々。","salesDate":"2013年08月","itemPrice":900,"listPrice":900,"discountRate":0,"discountPrice":0,"itemUrl":"http://books.rakuten.co.jp/rb/12389357/","affiliateUrl":"","smallImageUrl":"http://thumbnail.image.rakuten.co.jp/@0_mall/book/cabinet/4201/9784883864201.jpg?_ex=64x64","mediumImageUrl":"http://thumbnail.image.rakuten.co.jp/@0_mall/book/cabinet/4201/9784883864201.jpg?_ex=120x120","largeImageUrl":"http://thumbnail.image.rakuten.co.jp/@0_mall/book/cabinet/4201/9784883864201.jpg?_ex=200x200","chirayomiUrl":"","availability":"1","postageFlag":0,"limitedFlag":0,"reviewCount":0,"reviewAverage":"0.0","booksGenreId":"001004008001"}},{"Item":{"title":"十面相","titleKana":"ジュウメンソウ","subTitle":"","subTitleKana":"","seriesName":"","seriesNameKana":"","contents":"","author":"ＹＭ/鷹村コージ","authorKana":"ワイエム/タカムラ,コージ","publisherName":"一迅社","size":"新書","isbn":"9784758044677","itemCaption":"あの人気楽曲『十面相』が待望の小説化。『十面相』収録ＣＤ付き。","salesDate":"2013年08月01日","itemPrice":1260,"listPrice":1260,"discountRate":0,"discountPrice":0,"itemUrl":"http://books.rakuten.co.jp/rb/12351474/","affiliateUrl":"","smallImageUrl":"http://thumbnail.image.rakuten.co.jp/@0_mall/book/cabinet/4677/9784758044677.jpg?_ex=64x64","mediumImageUrl":"http://thumbnail.image.rakuten.co.jp/@0_mall/book/cabinet/4677/9784758044677.jpg?_ex=120x120","largeImageUrl":"http://thumbnail.image.rakuten.co.jp/@0_mall/book/cabinet/4677/9784758044677.jpg?_ex=200x200","chirayomiUrl":"","availability":"1","postageFlag":0,"limitedFlag":0,"reviewCount":0,"reviewAverage":"0.0","booksGenreId":"001004008004/001004008008"}},{"Item":{"title":"仁義なき嫁（新妻編）","titleKana":"ジンギ ナキ ヨメ","subTitle":"","subTitleKana":"","seriesName":"ＡＺ　ｎｏｖｅｌｓ","seriesNameKana":"アズ ノベルズ","contents":"","author":"高月紅葉","authorKana":"コウズキ,モミジ","publisherName":"イースト・プレス","size":"新書","isbn":"9784781610337","itemCaption":"『こおろぎ組の狂犬』こと佐和紀が組存続のため、大滝組若頭補佐・岩下周平のもとに嫁入りしてからニヶ月。新婚旅行先の熱海では周平から遅ればせながらプロポーズの言葉とともにダイヤの指輪を贈られ、アツアツムード全開…のはずが、佐和紀には一つ不満が。というのも、挙式以来挿入はたったの三回！おまけに情人の美少年・ユウキともまだ切れていないみたいで…。手負いの獣よろしく苛立つ新妻、佐和紀だが…。","salesDate":"2013年08月","itemPrice":893,"listPrice":893,"discountRate":0,"discountPrice":0,"itemUrl":"http://books.rakuten.co.jp/rb/12411532/","affiliateUrl":"","smallImageUrl":"http://thumbnail.image.rakuten.co.jp/@0_mall/book/cabinet/0337/9784781610337.jpg?_ex=64x64","mediumImageUrl":"http://thumbnail.image.rakuten.co.jp/@0_mall/book/cabinet/0337/9784781610337.jpg?_ex=120x120","largeImageUrl":"http://thumbnail.image.rakuten.co.jp/@0_mall/book/cabinet/0337/9784781610337.jpg?_ex=200x200","chirayomiUrl":"","availability":"1","postageFlag":0,"limitedFlag":0,"reviewCount":0,"reviewAverage":"0.0","booksGenreId":"001004008002/001021001013"}},{"Item":{"title":"真田軍戦記（3）","titleKana":"サナダ グンセンキ","subTitle":"","subTitleKana":"","seriesName":"歴史群像新書","seriesNameKana":"レキシ グンゾウ シンショ","contents":"総攻撃！船場大戦","author":"津野田幸作","authorKana":"ツノダ,コウサク","publisherName":"学研パブリッシング","size":"新書","isbn":"9784054057548","itemCaption":"幸村野戦を決断す！大阪城外決戦開始！！船場の福島軍を徳川軍から守るべく、秀頼ついに総大将として出陣！！九鬼水軍、淀川より襲来！大筒攻撃炸烈す！！本格戦国シミュレーション。","salesDate":"2013年07月下旬","itemPrice":980,"listPrice":980,"discountRate":0,"discountPrice":0,"itemUrl":"http://books.rakuten.co.jp/rb/12355807/","affiliateUrl":"","smallImageUrl":"http://thumbnail.image.rakuten.co.jp/@0_mall/book/cabinet/7548/9784054057548.jpg?_ex=64x64","mediumImageUrl":"http://thumbnail.image.rakuten.co.jp/@0_mall/book/cabinet/7548/9784054057548.jpg?_ex=120x120","largeImageUrl":"http://thumbnail.image.rakuten.co.jp/@0_mall/book/cabinet/7548/9784054057548.jpg?_ex=200x200","chirayomiUrl":"","availability":"1","postageFlag":0,"limitedFlag":0,"reviewCount":0,"reviewAverage":"0.0","booksGenreId":"001004008004"}},{"Item":{"title":"トゥルークの海賊2","titleKana":"トゥルークノカイゾク2","subTitle":"","subTitleKana":"","seriesName":"Ｃ・ｎｏｖｅｌｓ　ｆａｎｔａｓｉａ","seriesNameKana":"シー ノベルス ファンタジア","contents":"","author":"茅田砂胡","authorKana":"カヤタ,スナコ","publisherName":"中央公論新社","size":"新書","isbn":"9784125012551","itemCaption":"“パラス・アテナ”の前に武装した八隻の宇宙船がずらりと並んでいた。二代目グランド・セヴン達の船と、“ブラック・スワン”二世号とが。探索の依頼を受けてトゥルークに赴いた怪獣夫婦は連邦軍の駆逐隊が壊滅する現場に行き合う。その襲撃者は恥知らずにも伝説の大海賊の名を口にした。-その時、ケリーの顔から表情が消えた。一方、大いなる闇の顕現を告げられたトゥルークの僧侶たちは大混乱。ついにはサリース・ゴオランの僧籍離脱問題へと発展…？内憂外患（！？）な惑星トゥルークの第２弾！","salesDate":"2013年07月下旬","itemPrice":945,"listPrice":945,"discountRate":0,"discountPrice":0,"itemUrl":"http://books.rakuten.co.jp/rb/12359070/","affiliateUrl":"","smallImageUrl":"http://thumbnail.image.rakuten.co.jp/@0_mall/book/cabinet/2551/9784125012551.jpg?_ex=64x64","mediumImageUrl":"http://thumbnail.image.rakuten.co.jp/@0_mall/book/cabinet/2551/9784125012551.jpg?_ex=120x120","largeImageUrl":"http://thumbnail.image.rakuten.co.jp/@0_mall/book/cabinet/2551/9784125012551.jpg?_ex=200x200","chirayomiUrl":"","availability":"1","postageFlag":0,"limitedFlag":0,"reviewCount":31,"reviewAverage":"4.39","booksGenreId":"001004008002/001017006010"}},{"Item":{"title":"興国の楯1945（工作艦『須磨』爆撃作戦！）","titleKana":"コウコク ノ タテ センキュウヒャク シジュウゴ","subTitle":"通商護衛機動艦隊","subTitleKana":"ツウショウ ゴエイ キドウ カンタイ","seriesName":"歴史群像新書","seriesNameKana":"レキシ グンゾウ シンショ","contents":"","author":"林譲治","authorKana":"ハヤシ,ジョウジ","publisherName":"学研パブリッシング","size":"新書","isbn":"9784054057531","itemCaption":"日本軍に撃破・鹵獲されたソ連戦艦『ミズーリ』の修復のためアッツ島へ向かった工作艦『須磨』。『ミズーリ』復旧を阻止せんと、ソ連は誘導爆弾搭載の爆撃機隊を放った！","salesDate":"2013年07月下旬","itemPrice":980,"listPrice":980,"discountRate":0,"discountPrice":0,"itemUrl":"http://books.rakuten.co.jp/rb/12355806/","affiliateUrl":"","smallImageUrl":"http://thumbnail.image.rakuten.co.jp/@0_mall/book/cabinet/7531/9784054057531.jpg?_ex=64x64","mediumImageUrl":"http://thumbnail.image.rakuten.co.jp/@0_mall/book/cabinet/7531/9784054057531.jpg?_ex=120x120","largeImageUrl":"http://thumbnail.image.rakuten.co.jp/@0_mall/book/cabinet/7531/9784054057531.jpg?_ex=200x200","chirayomiUrl":"","availability":"1","postageFlag":0,"limitedFlag":0,"reviewCount":0,"reviewAverage":"0.0","booksGenreId":"001004008006"}},{"Item":{"title":"幻の八八艦隊","titleKana":"マボロシ ノ ハチハチ カンタイ","subTitle":"","subTitleKana":"","seriesName":"歴史群像新書","seriesNameKana":"レキシ グンゾウ シンショ","contents":"","author":"齊藤拓樹","authorKana":"サイトウ,ヒロキ","publisherName":"学研パブリッシング","size":"新書","isbn":"9784054057555","itemCaption":"１９４１年１２月５日、日豪ｖｓ．米の壮絶なる死闘の火ぶたが切られた！本格リアルシミュレーション戦記！","salesDate":"2013年07月下旬","itemPrice":990,"listPrice":990,"discountRate":0,"discountPrice":0,"itemUrl":"http://books.rakuten.co.jp/rb/12355808/","affiliateUrl":"","smallImageUrl":"http://thumbnail.image.rakuten.co.jp/@0_mall/book/cabinet/7555/9784054057555.jpg?_ex=64x64","mediumImageUrl":"http://thumbnail.image.rakuten.co.jp/@0_mall/book/cabinet/7555/9784054057555.jpg?_ex=120x120","largeImageUrl":"http://thumbnail.image.rakuten.co.jp/@0_mall/book/cabinet/7555/9784054057555.jpg?_ex=200x200","chirayomiUrl":"","availability":"1","postageFlag":0,"limitedFlag":0,"reviewCount":0,"reviewAverage":"0.0","booksGenreId":"001004008003"}},{"Item":{"title":"日中尖閣戦争","titleKana":"ニッチュウ センカク センソウ","subTitle":"","subTitleKana":"","seriesName":"歴史群像新書","seriesNameKana":"レキシ グンゾウ シンショ","contents":"","author":"中村ケイジ","authorKana":"ナカムラ,ケイジ","publisherName":"学研パブリッシング","size":"新書","isbn":"9784054056718","itemCaption":"「打倒、小日本！」中国東海艦隊出撃！！２０１Ｘ年、尖閣諸島はついに灼熱の劫火に包まれた！！！近未来戦記シミュレーションの白眉！","salesDate":"2013年07月下旬","itemPrice":990,"listPrice":990,"discountRate":0,"discountPrice":0,"itemUrl":"http://books.rakuten.co.jp/rb/12355804/","affiliateUrl":"","smallImageUrl":"http://thumbnail.image.rakuten.co.jp/@0_mall/book/cabinet/6718/9784054056718.jpg?_ex=64x64","mediumImageUrl":"http://thumbnail.image.rakuten.co.jp/@0_mall/book/cabinet/6718/9784054056718.jpg?_ex=120x120","largeImageUrl":"http://thumbnail.image.rakuten.co.jp/@0_mall/book/cabinet/6718/9784054056718.jpg?_ex=200x200","chirayomiUrl":"","availability":"1","postageFlag":0,"limitedFlag":0,"reviewCount":0,"reviewAverage":"0.0","booksGenreId":"001004008005"}},{"Item":{"title":"異　帝国太平洋戦争9","titleKana":"イ テイコク タイヘイヨウ センソウ","subTitle":"","subTitleKana":"","seriesName":"歴史群像新書","seriesNameKana":"レキシ グンゾウ シンショ","contents":"","author":"羅門祐人","authorKana":"ラモン,ユウト","publisherName":"学研パブリッシング","size":"新書","isbn":"9784054057524","itemCaption":"大和・武蔵ｖｓアイオワ級４隻の大艦砲戦！ミッドウェイの敵前上陸を前に連合艦隊の島をゆるがす主砲弾！羅門ワールドの新境地！","salesDate":"2013年07月下旬","itemPrice":980,"listPrice":980,"discountRate":0,"discountPrice":0,"itemUrl":"http://books.rakuten.co.jp/rb/12355805/","affiliateUrl":"","smallImageUrl":"http://thumbnail.image.rakuten.co.jp/@0_mall/book/cabinet/7524/9784054057524.jpg?_ex=64x64","mediumImageUrl":"http://thumbnail.image.rakuten.co.jp/@0_mall/book/cabinet/7524/9784054057524.jpg?_ex=120x120","largeImageUrl":"http://thumbnail.image.rakuten.co.jp/@0_mall/book/cabinet/7524/9784054057524.jpg?_ex=200x200","chirayomiUrl":"","availability":"1","postageFlag":0,"limitedFlag":0,"reviewCount":0,"reviewAverage":"0.0","booksGenreId":"001004008008"}},{"Item":{"title":"閃乱カグラ","titleKana":"センラン カグラ","subTitle":"少女達の青春","subTitleKana":"ショウジョタチ ノ セイシュン","seriesName":"ＤＭＣ　ｎｏｖｅｌｓ","seriesNameKana":"ディーエムシー ノベルズ","contents":"","author":"にのまえあゆむ/高木謙一郎","authorKana":"ニノマエ,アユム/タカキ,ケンイチロウ","publisherName":"一迅社","size":"新書","isbn":"9784758044394","itemCaption":"温泉旅館の露天風呂で蛇女の焔たちと出会った飛鳥たち半蔵学院一行。温泉宿に来てまで訓練していた焔は、汗まみれの泥まみれ。そこで飛鳥は彼女を自分たちが泊まる部屋の内風呂へ案内することにした。緊張する焔を和らげようと、飛鳥がプロポーションの話題を振ったことで始まるおっぱい談議！？爆乳ハイパーバトルが小説になっていよいよ登場！ＴＶアニメ化もされた大ヒットゲーム『閃乱カグラ』シリーズをノベライズ！『飛鳥＆焔の章』ほか短編５編収録。","salesDate":"2013年07月27日","itemPrice":890,"listPrice":890,"discountRate":0,"discountPrice":0,"itemUrl":"http://books.rakuten.co.jp/rb/12355803/","affiliateUrl":"","smallImageUrl":"http://thumbnail.image.rakuten.co.jp/@0_mall/book/cabinet/4394/9784758044394.jpg?_ex=64x64","mediumImageUrl":"http://thumbnail.image.rakuten.co.jp/@0_mall/book/cabinet/4394/9784758044394.jpg?_ex=120x120","largeImageUrl":"http://thumbnail.image.rakuten.co.jp/@0_mall/book/cabinet/4394/9784758044394.jpg?_ex=200x200","chirayomiUrl":"","availability":"1","postageFlag":0,"limitedFlag":0,"reviewCount":0,"reviewAverage":"0.0","booksGenreId":"001004008004/001004008005"}},{"Item":{"title":"日光鬼怒川殺人事件","titleKana":"ニッコウ キヌガワ サツジン ジケン","subTitle":"旅行作家・茶屋次郎の事件簿","subTitleKana":"リョコウ サッカ チャヤ ジロウ ノ ジケンボ","seriesName":"Ｎｏｎ　ｎｏｖｅｌ","seriesNameKana":"ノン ノベル","contents":"","author":"梓林太郎","authorKana":"アズサ,リンタロウ","publisherName":"祥伝社","size":"新書","isbn":"9784396210083","itemCaption":"旅行作家・茶屋次郎の友人糸島が北アルプスで遭難死した。山に詳しい仕事仲間金堀に連れて行かれたのだが、糸島のみが死んでしまったという。茶屋はその死に疑問を抱き、登ったルートを確認。やはり故意に道を誤り、遭難させたのではという確信を得た。金堀の身辺を探るべく、鬼怒川へと赴いた茶屋。しかしその地で、遭難死に同じ疑問を持った女性が川に転落死し、殺人容疑が茶屋へと向けられたーその後も続く惨劇、女の魔性に翻弄される茶屋は真相に辿り着けるのか。世界遺産・日光の魅力も描いた旅情ミステリー。","salesDate":"2013年07月25日","itemPrice":880,"listPrice":880,"discountRate":0,"discountPrice":0,"itemUrl":"http://books.rakuten.co.jp/rb/12383699/","affiliateUrl":"","smallImageUrl":"http://thumbnail.image.rakuten.co.jp/@0_mall/book/cabinet/0083/9784396210083.jpg?_ex=64x64","mediumImageUrl":"http://thumbnail.image.rakuten.co.jp/@0_mall/book/cabinet/0083/9784396210083.jpg?_ex=120x120","largeImageUrl":"http://thumbnail.image.rakuten.co.jp/@0_mall/book/cabinet/0083/9784396210083.jpg?_ex=200x200","chirayomiUrl":"","availability":"1","postageFlag":0,"limitedFlag":0,"reviewCount":0,"reviewAverage":"0.0","booksGenreId":"001004008001"}},{"Item":{"title":"彷徨う勇者魔王に花","titleKana":"サマヨウ ユウシャ マオウ ニ ハナ","subTitle":"","subTitleKana":"","seriesName":"Ｃ・ｎｏｖｅｌｓ　ｆａｎｔａｓｉａ","seriesNameKana":"シー ノベルス ファンタジア","contents":"","author":"沙藤菫","authorKana":"サトウ,スミレ","publisherName":"中央公論新社","size":"新書","isbn":"9784125012575","itemCaption":"魔帝の母と人間の父の間に生まれた七人兄弟の末っ子アランは、人の世で助けた娘オリガに恋をした。想いが叶わぬときは砂になるー制約付きで人間になれる薬を呑み、「帰りたい」という彼女の願いを叶えようと奮闘する。旅の途中、魔に襲われ逃げまどう人々を背に庇い、立ち向かったオリガ。彼女の正体は魔帝を殺す使命を帯びた勇者だったのだ！魔王アランも彼女の標的で…。第９回Ｃ・ＮＯＶＥＬＳ大賞特別賞受賞作。","salesDate":"2013年07月25日","itemPrice":945,"listPrice":945,"discountRate":0,"discountPrice":0,"itemUrl":"http://books.rakuten.co.jp/rb/12359072/","affiliateUrl":"","smallImageUrl":"http://thumbnail.image.rakuten.co.jp/@0_mall/book/cabinet/2575/9784125012575.jpg?_ex=64x64","mediumImageUrl":"http://thumbnail.image.rakuten.co.jp/@0_mall/book/cabinet/2575/9784125012575.jpg?_ex=120x120","largeImageUrl":"http://thumbnail.image.rakuten.co.jp/@0_mall/book/cabinet/2575/9784125012575.jpg?_ex=200x200","chirayomiUrl":"","availability":"1","postageFlag":0,"limitedFlag":0,"reviewCount":0,"reviewAverage":"0.0","booksGenreId":"001004008003/001017006010"}},{"Item":{"title":"英雄《竜殺し》の終焉","titleKana":"エイユウ リュウゴロシ ノ シュウエン","subTitle":"","subTitleKana":"","seriesName":"Ｃ・ｎｏｖｅｌｓ　ｆａｎｔａｓｉａ","seriesNameKana":"シー ノベルス ファンタジア","contents":"","author":"戒能靖十郎","authorKana":"カイノウ,セイジュウロウ","publisherName":"中央公論新社","size":"新書","isbn":"9784125012568","itemCaption":"交易都市クリザの領主は、かつて大陸を襲った竜を倒した英雄アルズレッド。富も名声も手に入れた英雄だが、闘いに身を置いてきた彼には、今の平和な暮らしは退屈の連続でしかない。古くから仕える執事と侍女のみが彼の厭世を知り、気に病んでいた。そんなある日、屋敷に現れたのは完全に白い謎の存在。“白の狩人”と名乗り、「黒」を狩ると言うのだが…！？第９回Ｃ・ＮＯＶＥＬＳ大賞特別賞受賞作。","salesDate":"2013年07月25日","itemPrice":945,"listPrice":945,"discountRate":0,"discountPrice":0,"itemUrl":"http://books.rakuten.co.jp/rb/12359071/","affiliateUrl":"","smallImageUrl":"http://thumbnail.image.rakuten.co.jp/@0_mall/book/cabinet/2568/9784125012568.jpg?_ex=64x64","mediumImageUrl":"http://thumbnail.image.rakuten.co.jp/@0_mall/book/cabinet/2568/9784125012568.jpg?_ex=120x120","largeImageUrl":"http://thumbnail.image.rakuten.co.jp/@0_mall/book/cabinet/2568/9784125012568.jpg?_ex=200x200","chirayomiUrl":"","availability":"1","postageFlag":0,"limitedFlag":0,"reviewCount":0,"reviewAverage":"0.0","booksGenreId":"001004008002/001017006010"}},{"Item":{"title":"特務捜査ハラスメント","titleKana":"トクム ソウサ ハラスメント","subTitle":"絶頂酔い牝デビュー","subTitleKana":"イキヨイ メス デビュー","seriesName":"二次元ドリームノベルズ","seriesNameKana":"ニジゲン ドリーム ノベルズ","contents":"","author":"神楽陽子/こうきくう","authorKana":"カグラ,ヨウコ/こうきくう","publisherName":"キルタイムコミュニケーション","size":"新書","isbn":"9784799204436","itemCaption":"新警特務署の特務４課に所属する、奏乃葉昴と錫城真琴。全体的な腐敗が潜む新警の中で、市民人気も高い彼女たちが挑むのは、勢力を拡大しつつあるマフィア、ビシディア商会への立ち入り捜査だった。新警上層部との癒着も囁かれる黒い関係を暴こうとするも、潜入中に捕らわれ、ぶっかけやフェラによって牡の味を覚えこまされる二人。さらに痴漢や乱交が続く恥辱捜査に解決の時は訪れるのか？","salesDate":"2013年07月23日","itemPrice":935,"listPrice":935,"discountRate":0,"discountPrice":0,"itemUrl":"http://books.rakuten.co.jp/rb/12373935/","affiliateUrl":"","smallImageUrl":"http://thumbnail.image.rakuten.co.jp/@0_mall/book/cabinet/4436/9784799204436.jpg?_ex=64x64","mediumImageUrl":"http://thumbnail.image.rakuten.co.jp/@0_mall/book/cabinet/4436/9784799204436.jpg?_ex=120x120","largeImageUrl":"http://thumbnail.image.rakuten.co.jp/@0_mall/book/cabinet/4436/9784799204436.jpg?_ex=200x200","chirayomiUrl":"","availability":"1","postageFlag":0,"limitedFlag":0,"reviewCount":0,"reviewAverage":"0.0","booksGenreId":"001004008009/001008022008"}},{"Item":{"title":"ハイ・フロンティア","titleKana":"ハイ フロンティア","subTitle":"","subTitleKana":"","seriesName":"朝日ノベルズ","seriesNameKana":"アサヒ ノベルズ","contents":"","author":"笹本祐一/笹本祐一","authorKana":"ササモト,ユウイチ/ササモト,ユウイチ","publisherName":"朝日新聞出版","size":"新書","isbn":"9784022760043","itemCaption":"新たなミッションのために飛び立った美紀たちだったが、会社は爆破予告を受け、乗った飛行機は射撃レーダーに狙われた。突然の凶報から始まる謎の行方とは！？そして、天才少女学者スウがもたらした情報から、全世界が一つの目標へと動き始めるー。『ミニスカ宇宙海賊』著者の伝説のシリーズ、ノベルズ新装版完結編。宇宙をかけめぐる飛行士たちの夢が、いま現実となる。","salesDate":"2013年07月19日","itemPrice":1470,"listPrice":1470,"discountRate":0,"discountPrice":0,"itemUrl":"http://books.rakuten.co.jp/rb/12382343/","affiliateUrl":"","smallImageUrl":"http://thumbnail.image.rakuten.co.jp/@0_mall/book/cabinet/0043/9784022760043.jpg?_ex=64x64","mediumImageUrl":"http://thumbnail.image.rakuten.co.jp/@0_mall/book/cabinet/0043/9784022760043.jpg?_ex=120x120","largeImageUrl":"http://thumbnail.image.rakuten.co.jp/@0_mall/book/cabinet/0043/9784022760043.jpg?_ex=200x200","chirayomiUrl":"http://books.rakuten.co.jp/chirayomi/index.phtml?id=7a7v1s056D&path=85/-1d0b6A&iid=9784022760043","availability":"1","postageFlag":0,"limitedFlag":0,"reviewCount":0,"reviewAverage":"0.0","booksGenreId":"001004008003/001017005005"}},{"Item":{"title":"吸血鬼と精神分析","titleKana":"キュウケツキ ト セイシン ブンセキ","subTitle":"","subTitleKana":"","seriesName":"Ｋａｐｐａ　ｎｏｖｅｌｓ","seriesNameKana":"カッパ ノベルス","contents":"","author":"笠井潔","authorKana":"カサイ,キヨシ","publisherName":"光文社","size":"新書","isbn":"9784334077167","itemCaption":"バスティーユにある要塞のようなアパルトマンで、ルーマニアからの亡命者が惨殺される。床には“ＤＲＡＣ”の血文字が残されていた。そして、パリ市東部のヴァンセンヌの森では女性の焼屍体が発見され、その躰からはすべての血が抜かれていた。続く第二、第三の失血殺人。亡命者殺害と連続殺人の関連は！？一方、体調不良が続く女子大生ナディアは精神医のもとを訪れたところ、そこでタチアナという女性から奇妙な依頼を受ける。一連の出来事がつながったとき、そこには意外な真相がー。ナディアの友人・矢吹駆が事件の謎に迫る！待望のノベルス版刊行！","salesDate":"2013年07月19日","itemPrice":1470,"listPrice":1470,"discountRate":0,"discountPrice":0,"itemUrl":"http://books.rakuten.co.jp/rb/12380455/","affiliateUrl":"","smallImageUrl":"http://thumbnail.image.rakuten.co.jp/@0_mall/book/cabinet/7167/9784334077167.jpg?_ex=64x64","mediumImageUrl":"http://thumbnail.image.rakuten.co.jp/@0_mall/book/cabinet/7167/9784334077167.jpg?_ex=120x120","largeImageUrl":"http://thumbnail.image.rakuten.co.jp/@0_mall/book/cabinet/7167/9784334077167.jpg?_ex=200x200","chirayomiUrl":"","availability":"1","postageFlag":0,"limitedFlag":0,"reviewCount":0,"reviewAverage":"0.0","booksGenreId":"001004008002"}},{"Item":{"title":"ヒカルセカイ","titleKana":"ヒカル セカイ","subTitle":"","subTitleKana":"","seriesName":"Ｙｕｒｉ-Ｈｉｍｅ　Ｎｏｖｅｌ","seriesNameKana":"ユリヒメ ノベル","contents":"","author":"雨降波近/タカハシマコ","authorKana":"アマフリ,ナミチカ","publisherName":"一迅社","size":"新書","isbn":"9784758072694","itemCaption":"不幸の女神候補・ミレットは、神様になるために「不幸な人間に近づきさらに不幸にして殺す」という試練が与えられた。人間界に降り立ちターゲットに選んだのは、ガールズ・プログレバンドで活動する女子高生・彩乃。両親を亡くし日常も不幸なアクシデントばかりなのにおおらかな性格の彼女は、ミレットとの同居をすんなりＯＫし、ふたりの新たな生活が始まった。彩乃の高校にも転校！？し、バンドメンバーとも交流を深めるミレットは、いつしかこの日常が続くように、そして彩乃の幸福を望むようになるのだが…。一迅社文庫アイリス少女小説大賞応募作品を、大幅に加筆修正。期待の新鋭の百合ノベルデビュー作品。","salesDate":"2013年07月18日","itemPrice":1575,"listPrice":1575,"discountRate":0,"discountPrice":0,"itemUrl":"http://books.rakuten.co.jp/rb/12357489/","affiliateUrl":"","smallImageUrl":"http://thumbnail.image.rakuten.co.jp/@0_mall/book/cabinet/2694/9784758072694.jpg?_ex=64x64","mediumImageUrl":"http://thumbnail.image.rakuten.co.jp/@0_mall/book/cabinet/2694/9784758072694.jpg?_ex=120x120","largeImageUrl":"http://thumbnail.image.rakuten.co.jp/@0_mall/book/cabinet/2694/9784758072694.jpg?_ex=200x200","chirayomiUrl":"","availability":"1","postageFlag":1,"limitedFlag":0,"reviewCount":0,"reviewAverage":"0.0","booksGenreId":"001004008001"}}],"GenreInformation":[]}